diffct/__init__.py
diffct/differentiable.py
diffct-1.2.7.dist-info/METADATA
diffct-1.2.7.dist-info/WHEEL
diffct-1.2.7.dist-info/licenses/LICENSE
diffct-1.2.7.dist-info/RECORD
