Metadata-Version: 2.4
Name: diffct
Version: 1.2.7
Summary: A CUDA-based library for computed tomography (CT) projection and reconstruction with differentiable operators
Project-URL: Homepage, https://github.com/sypsyp97/diffct
Author-email: Yipeng Sun <yipeng.sun@fau.de>
License: Apache 2.0
License-File: LICENSE
Classifier: License :: OSI Approved :: Apache Software License
Classifier: Operating System :: OS Independent
Classifier: Programming Language :: Python :: 3
Classifier: Topic :: Scientific/Engineering :: Medical Science Apps.
Requires-Dist: numba
Requires-Dist: numpy
Requires-Dist: torch
